py2mermaid/__init__.py
py2mermaid/chart.py
py2mermaid/utils.py
py2mermaid-0.2.0.dist-info/licenses/LICENSE.txt
py2mermaid-0.2.0.dist-info/METADATA
py2mermaid-0.2.0.dist-info/WHEEL
py2mermaid-0.2.0.dist-info/top_level.txt
py2mermaid-0.2.0.dist-info/RECORD
