Metadata-Version: 2.4
Name: py2mermaid
Version: 0.2.0
Summary: A Python helper library to create Mermaid.js diagrams
Home-page: https://github.com/raghuvasanthrao/mermaidpy
Author: raghuvasanthrao
Author-email: k.s.raghuvsanthrao@gmail.com
Classifier: Programming Language :: Python :: 3
Classifier: License :: OSI Approved :: MIT License
Requires-Python: >=3.6
License-File: LICENSE.txt
Dynamic: author
Dynamic: author-email
Dynamic: classifier
Dynamic: description
Dynamic: description-content-type
Dynamic: home-page
Dynamic: license-file
Dynamic: requires-python
Dynamic: summary
